dialogue/__init__.py
dialogue/dialogue.py
dialogue/dialogue_test.py
dialogue_tester-1.0b5.dist-info/LICENSE
dialogue_tester-1.0b5.dist-info/METADATA
dialogue_tester-1.0b5.dist-info/WHEEL
dialogue_tester-1.0b5.dist-info/top_level.txt
dialogue_tester-1.0b5.dist-info/RECORD
