Metadata-Version: 2.1
Name: dialogue-tester
Version: 1.0b5
Summary: Dialogue class for testing REPLs
Home-page: https://github.com/ramalho/dialogue
Author: Luciano Ramalho
License: UNKNOWN
Platform: UNKNOWN
Classifier: Programming Language :: Python :: 3.7
Classifier: License :: OSI Approved :: BSD License
Classifier: Operating System :: OS Independent
Classifier: Topic :: Software Development :: Testing
